geofem/__init__.py
geofem/MCSEM/__init__.py
geofem/MCSEM/core.py
geofem/MCSEM/fields.py
geofem/MCSEM/io.py
geofem/MCSEM/maps.py
geofem/MCSEM/meshes.py
geofem/MCSEM/models.py
geofem/MCSEM/solver.py
geofem/MCSEM/utils.py
geofem/MCSEM/version.py
geofem/MT/DataMisfit.py
geofem/MT/Directives.py
geofem/MT/Fields.py
geofem/MT/InvProblem.py
geofem/MT/Inversion.py
geofem/MT/Maps.py
geofem/MT/Models.py
geofem/MT/ObjectiveFunction.py
geofem/MT/Optimization.py
geofem/MT/Problem.py
geofem/MT/Props.py
geofem/MT/Survey.py
geofem/MT/__init__.py
geofem/MT/EM/Base.py
geofem/MT/EM/__init__.py
geofem/MT/EM/Analytics/DC.py
geofem/MT/EM/Analytics/FDEM.py
geofem/MT/EM/Analytics/FDEMDipolarfields.py
geofem/MT/EM/Analytics/FDEMcasing.py
geofem/MT/EM/Analytics/NSEM.py
geofem/MT/EM/Analytics/TDEM.py
geofem/MT/EM/Analytics/__init__.py
geofem/MT/EM/FDEM/FieldsFDEM.py
geofem/MT/EM/FDEM/ProblemFDEM.py
geofem/MT/EM/FDEM/RxFDEM.py
geofem/MT/EM/FDEM/SrcFDEM.py
geofem/MT/EM/FDEM/SurveyFDEM.py
geofem/MT/EM/FDEM/__init__.py
geofem/MT/EM/NSEM/FieldsNSEM.py
geofem/MT/EM/NSEM/ProblemNSEM.py
geofem/MT/EM/NSEM/RxNSEM.py
geofem/MT/EM/NSEM/SrcNSEM.py
geofem/MT/EM/NSEM/SurveyNSEM.py
geofem/MT/EM/NSEM/__init__.py
geofem/MT/EM/NSEM/Utils/MT1Danalytic.py
geofem/MT/EM/NSEM/Utils/MT1Dsolutions.py
geofem/MT/EM/NSEM/Utils/__init__.py
geofem/MT/EM/NSEM/Utils/dataUtils.py
geofem/MT/EM/NSEM/Utils/data_viewer.py
geofem/MT/EM/NSEM/Utils/ediFilesUtils.py
geofem/MT/EM/NSEM/Utils/plotDataTypes.py
geofem/MT/EM/NSEM/Utils/plotUtils.py
geofem/MT/EM/NSEM/Utils/sourceUtils.py
geofem/MT/EM/NSEM/Utils/testUtils.py
geofem/MT/EM/NSEM_octree/FieldsNSEM.py
geofem/MT/EM/NSEM_octree/ProblemNSEM.py
geofem/MT/EM/NSEM_octree/RxNSEM.py
geofem/MT/EM/NSEM_octree/SrcNSEM.py
geofem/MT/EM/NSEM_octree/SurveyNSEM.py
geofem/MT/EM/NSEM_octree/__init__.py
geofem/MT/EM/NSEM_octree/Utils/MT1Danalytic.py
geofem/MT/EM/NSEM_octree/Utils/MT1Dsolutions.py
geofem/MT/EM/NSEM_octree/Utils/__init__.py
geofem/MT/EM/NSEM_octree/Utils/dataUtils.py
geofem-0.0.7.dist-info/LICENSE
geofem-0.0.7.dist-info/METADATA
geofem-0.0.7.dist-info/WHEEL
geofem-0.0.7.dist-info/top_level.txt
geofem-0.0.7.dist-info/RECORD
