Metadata-Version: 2.1
Name: geofem
Version: 0.0.7
Summary: Modelagem geofísica direta de campos eletromagnéticos via volumes finitos: MT e MCSEM.
Home-page: https://github.com/iisadoramacedo/geofem-master
Author: Isadora
Author-email: isadora.s.macedo@gmail.com
License: UNKNOWN
Download-URL: https://github.com/iisadoramacedo/geofem-master/archive/v0.0.7.tar.gz
Platform: UNKNOWN
Classifier: Programming Language :: Python :: 3
Classifier: License :: OSI Approved :: MIT License
Classifier: Operating System :: Unix
Requires-Python: >=3.7
Requires-Dist: numpy (>=1.7)
Requires-Dist: scipy (>=1.4.0)
Requires-Dist: pymatsolver (>=0.1.1)
Requires-Dist: matplotlib
Requires-Dist: pyvista
Requires-Dist: properties (>=0.5.2)
Requires-Dist: vectormath (>=0.2.0)
Requires-Dist: discretize (>=0.4.0)
Requires-Dist: geoana (>=0.0.4)
Requires-Dist: empymod (>=2.0.0)
Requires-Dist: pandas
Requires-Dist: numba (>=0.45.0)
